{
  "type": "minecraft:spline",
  "spline": {
    "coordinate": "minecraft:river/overground",
    "points": [
      {
        "location": 0.1,
        "derivative": 0,
        "value": 1
      },
      {
        "location": 0.2,
        "derivative": 0,
        "value": {
          "coordinate": "minecraft:river/underground",
          "points": [
            {
              "location": 0.4,
              "derivative": 0,
              "value": 1
            },
            {
              "location": 1,
              "derivative": 0,
              "value": -1
            }
          ]
        }
      }
    ]
  }
}
